service_updater/__main__.py
service_updater/service_update.py
service_updater/tst_async.py
service_updater/providers/__init__.py
service_updater/providers/agentdvr.py
service_updater/providers/bazarr.py
service_updater/providers/esphome.py
service_updater/providers/homeassistant.py
service_updater/providers/pihole.py
service_updater/providers/plex.py
service_updater/providers/radarr.py
service_updater/providers/sonarr.py
service_updater/providers/zigbee2mqtt.py
service_updater-2022.11.4.dist-info/LICENSE.md
service_updater-2022.11.4.dist-info/METADATA
service_updater-2022.11.4.dist-info/WHEEL
service_updater-2022.11.4.dist-info/entry_points.txt
service_updater-2022.11.4.dist-info/top_level.txt
service_updater-2022.11.4.dist-info/RECORD
