Metadata-Version: 2.1
Name: service-updater
Version: 2022.11.4
Summary: Gather information about service updates
Author-email: bkbilly <bkbilly@hotmail.com>
Project-URL: Source Code, https://github.com/bkbilly/service-update-helper
Keywords: service_updater
Classifier: Programming Language :: Python :: 3
Classifier: License :: OSI Approved :: MIT License
Classifier: Operating System :: Unix
Requires-Python: >=3.7.0
License-File: LICENSE.md
Requires-Dist: beautifulsoup4 (>=4.8.1)
Requires-Dist: PyYAML (>=5.3.1)
Requires-Dist: ConfigArgParse (>=0.13.0)
Requires-Dist: paho-mqtt (>=1.5.1)
Requires-Dist: importlib-metadata (>=1.5.0)
Requires-Dist: aiohttp (>=3.8.1)
